LICENSE
README.md
setup.py
la_panic/__init__.py
la_panic/__main__.py
la_panic.egg-info/PKG-INFO
la_panic.egg-info/SOURCES.txt
la_panic.egg-info/dependency_links.txt
la_panic.egg-info/entry_points.txt
la_panic.egg-info/requires.txt
la_panic.egg-info/top_level.txt
la_panic/data_structure/__init__.py
la_panic/data_structure/raw_crash_stack.py
la_panic/panic_parser/__init__.py
la_panic/panic_parser/backtrace.py
la_panic/panic_parser/bug_type.py
la_panic/panic_parser/exception.py
la_panic/panic_parser/kernel_panic.py
la_panic/panic_parser/kernel_panic_full_type.py
la_panic/panic_parser/kext.py
la_panic/panic_parser/memory_status.py
la_panic/panic_parser/panic_parser.py
la_panic/panic_parser/process_list.py
la_panic/panic_parser/sliders.py
la_panic/panic_parser/socd_container.py
la_panic/panic_parser/versions.py
la_panic/panic_parser/zone.py
la_panic/panic_parser/addresses/__init__.py
la_panic/panic_parser/addresses/address_formater.py
la_panic/panic_parser/addresses/address_symbol_mapper.py
la_panic/panic_parser/addresses/la_address.py
la_panic/panic_parser/core_state/__init__.py
la_panic/panic_parser/core_state/abstract_core_state.py
la_panic/panic_parser/core_state/core_state.py
la_panic/panic_parser/core_state/crashed_core_state.py
la_panic/panic_parser/panic_specific/__init__.py
la_panic/panic_parser/panic_specific/kernel_force_reset_panic.py
la_panic/panic_parser/panic_specific/kernel_full_panic.py
la_panic/panic_parser/panic_specific/kernel_specific_base.py
la_panic/panic_parser/system/__init__.py
la_panic/panic_parser/system/system_manager.py
la_panic/utilities/__init__.py
la_panic/utilities/apple_date_time.py
la_panic/utilities/device_types.py
la_panic/utilities/design_pattern/__init__.py
la_panic/utilities/design_pattern/iteretable_with_last_object_signal.py
la_panic/utilities/design_pattern/singleton.py