Metadata-Version: 2.1
Name: la-panic
Version: 0.4.9
Summary: iPhone kernel panic parser
Home-page: https://gitlab.com/yanivhasbanidev/la_panic
Author: LoboAlpha
Classifier: Programming Language :: Python :: 3.7
Classifier: Programming Language :: Python :: 3.8
Classifier: Programming Language :: Python :: 3.9
Classifier: Programming Language :: Python :: 3.10
Classifier: Programming Language :: Python :: 3.11
License-File: LICENSE
